<?xml version="1.0" encoding="UTF-8"?>
<objects serializationModel="Studio.02.02.00">
	<object class="AudioFile" id="{f766d32c-d7fe-41ba-901c-eeee13225503}">
		<property name="assetPath">
			<value>UI Sfx/Wav/Slide_Soft_00.wav</value>
		</property>
		<property name="frequencyInKHz">
			<value>48</value>
		</property>
		<property name="channelCount">
			<value>1</value>
		</property>
		<property name="length">
			<value>0.877</value>
		</property>
		<relationship name="masterAssetFolder">
			<destination>{8c84fbdf-061b-4568-a3da-bd3f42c14c60}</destination>
		</relationship>
	</object>
</objects>
